setup.cfg
setup.py
scrybe/__init__.py
scrybe.egg-info/PKG-INFO
scrybe.egg-info/SOURCES.txt
scrybe.egg-info/dependency_links.txt
scrybe.egg-info/requires.txt
scrybe.egg-info/top_level.txt
scrybe/internal/__init__.py
scrybe/internal/api_util.py
scrybe/internal/auth.py
scrybe/internal/config.py
scrybe/internal/const.py
scrybe/internal/mapper.py
scrybe/internal/patch_imported_module.py
scrybe/internal/patcher.py
scrybe/internal/threading_util.py
scrybe/internal/util.py
scrybe/internal/code_capture/__init__.py
scrybe/internal/code_capture/source_code.py
scrybe/internal/code_capture/source_context.py
scrybe/internal/commons/__init__.py
scrybe/internal/commons/memory_logging_handler.py
scrybe/internal/commons/queue_item.py
scrybe/internal/depgraph/__init__.py
scrybe/internal/depgraph/lineage_graph.py
scrybe/internal/depgraph/node_util.py
scrybe/internal/depgraph/nodes.py
scrybe/internal/depgraph/ops.py
scrybe/internal/depgraph/tracking_graph.py
scrybe/internal/tracker/__init__.py
scrybe/internal/tracker/custom_model_param.py
scrybe/internal/tracker/dataset.py
scrybe/internal/tracker/grid_search.py
scrybe/internal/tracker/metrics.py
scrybe/internal/tracker/model.py
scrybe/internal/tracker/save_and_load_tracker.py
scrybe/internal/tracker/tracker_util.py
scrybe/internal/tracker/data/__init__.py
scrybe/internal/tracker/data/basic_iterator_util.py
scrybe/internal/tracker/data/missed_dataset_handler.py
scrybe/internal/tracker/data/utils.py
scrybe/internal/tracker/data/instrumentation/__init__.py
scrybe/internal/tracker/data/instrumentation/catboost_pool.py
scrybe/internal/tracker/data/instrumentation/import_interceptor.py
scrybe/internal/tracker/data/instrumentation/joblib_patch.py
scrybe/internal/tracker/data/instrumentation/numpy_datasets.py
scrybe/internal/tracker/data/instrumentation/pandas_datasets.py
scrybe/internal/tracker/data/instrumentation/spark_dataset.py
scrybe/internal/tracker/data/instrumentation/spark_util.py
scrybe/internal/tracker/nnet_decorator_func/__init__.py
scrybe/internal/tracker/nnet_decorator_func/callback.py
scrybe/internal/tracker/nnet_decorator_func/keras_callback.py
