Metadata-Version: 1.1
Name: scrybe
Version: 0.2.12
Summary: Automated Experiment Tracking to improve transparency, organisation and collaboration in DS/ML projects
Home-page: UNKNOWN
Author: scrybe.ml
Author-email: admin@scrybe.ml
License: UNKNOWN
Platform: UNKNOWN
Classifier: Development Status :: 5 - Production/Stable
Classifier: Intended Audience :: Developers
Classifier: Topic :: Software Development :: Build Tools
Classifier: Programming Language :: Python :: 3
Classifier: Programming Language :: Python :: 3.5
Classifier: Programming Language :: Python :: 3.6
Classifier: Programming Language :: Python :: 3.7
